{
  "scenario": "simultaneous-multi",
  "seed": 1234,
  "finish_time": 15000,
  "params": {
    "total_nodes": 50,
    "total_endpoints": 5,
    "total_subnets": 8,
    "total_layers": 4,
    "target_layer": 4,
    "total_database": 2,
    "terminate_compromise_ratio": 0.8,
    "scheme": "simultaneous",
    "mtd_interval": 700,
    "custom_strategies": null
  },
  "results": {
    "n_attack_events": 765,
    "n_mtd_events": 44,
    "n_compromised_hosts": 41,
    "host_compromise_ratio": 0.82,
    "sim_wallclock_seconds": 0.3963127136230469,
    "mtttc_eval_checkpoints": [
      {
        "time_to_compromise": 9.34295288056667,
        "attack_success_rate": 0.20833333333333334,
        "host_compromise_ratio": 0.06,
        "mtd_execution_frequency": 0.006097458476037891,
        "total_number_of_ports": 373,
        "attack_path_exposure": 0.41150000000000003,
        "roa": 0.04453250380648219,
        "shortest_path_variability": 0.0,
        "risk": 0.11149151690677413
      },
      {
        "time_to_compromise": 9.566634412241056,
        "attack_success_rate": 0.23809523809523808,
        "host_compromise_ratio": 0.12,
        "mtd_execution_frequency": 0.006097458476037891,
        "total_number_of_ports": 373,
        "attack_path_exposure": 0.41150000000000003,
        "roa": 0.04453250380648219,
        "shortest_path_variability": 0.0,
        "risk": 0.11149151690677413
      },
      {
        "time_to_compromise": 9.812559840524724,
        "attack_success_rate": 0.32608695652173914,
        "host_compromise_ratio": 0.16,
        "mtd_execution_frequency": 0.006097458476037891,
        "total_number_of_ports": 373,
        "attack_path_exposure": 0.41150000000000003,
        "roa": 0.04453250380648219,
        "shortest_path_variability": 0.0,
        "risk": 0.11149151690677413
      },
      {
        "time_to_compromise": 8.992583263665926,
        "attack_success_rate": 0.3448275862068966,
        "host_compromise_ratio": 0.22,
        "mtd_execution_frequency": 0.006097458476037891,
        "total_number_of_ports": 373,
        "attack_path_exposure": 0.41150000000000003,
        "roa": 0.04453250380648219,
        "shortest_path_variability": 0.0,
        "risk": 0.11149151690677413
      },
      {
        "time_to_compromise": 8.928464918448485,
        "attack_success_rate": 0.4032258064516129,
        "host_compromise_ratio": 0.26,
        "mtd_execution_frequency": 0.006097458476037891,
        "total_number_of_ports": 373,
        "attack_path_exposure": 0.41150000000000003,
        "roa": 0.04453250380648219,
        "shortest_path_variability": 0.0,
        "risk": 0.11149151690677413
      }
    ]
  },
  "versions": {
    "python": "3.11.15",
    "numpy": "2.4.3",
    "scipy": "1.17.1",
    "networkx": "3.6.1",
    "matplotlib": "3.10.8",
    "pandas": "3.0.2",
    "simpy": "4.1.1",
    "seaborn": "0.13.2"
  },
  "git": {
    "branch": "feat/metric-faithfulness",
    "head": "2032273d160943a634968f837329e7ba01edefca",
    "dirty": true
  }
}